metric/__init__.py
metric/metric.py
primemetricasync-1.1.dist-info/LICENSE.txt
primemetricasync-1.1.dist-info/METADATA
primemetricasync-1.1.dist-info/WHEEL
primemetricasync-1.1.dist-info/entry_points.txt
primemetricasync-1.1.dist-info/top_level.txt
primemetricasync-1.1.dist-info/RECORD
