Metadata-Version: 2.1
Name: primemetricasync
Version: 1.1
Summary: 📐 Prime Metric Demo CLI app Async
Author-email: Andrew Levin <author@example.com>
Maintainer-email: "A. Great Maintainer" <maintainer@example.com>
License: Copyright (c) 2016 The Python Packaging Authority (PyPA)
Project-URL: Homepage, https://github.com/andrewalevin/primemetric
Project-URL: Bug Reports, https://github.com/andrewalevin/primemetric/issues
Project-URL: Funding, https://donate.pypi.org
Project-URL: Say Thanks!, https://github.com/andrewalevin/primemetric
Project-URL: Source, https://github.com/andrewalevin/primemetric
Keywords: primemetric,sample,setuptools,development
Classifier: Development Status :: 3 - Alpha
Classifier: Intended Audience :: Developers
Classifier: Topic :: Software Development :: Build Tools
Classifier: License :: OSI Approved :: MIT License
Classifier: Programming Language :: Python :: 3
Classifier: Programming Language :: Python :: 3.8
Classifier: Programming Language :: Python :: 3.9
Classifier: Programming Language :: Python :: 3.10
Classifier: Programming Language :: Python :: 3.11
Classifier: Programming Language :: Python :: 3.12
Classifier: Programming Language :: Python :: 3 :: Only
Requires-Python: >=3.8
License-File: LICENSE.txt
Provides-Extra: dev
Requires-Dist: check-manifest ; extra == 'dev'
Provides-Extra: test
Requires-Dist: coverage ; extra == 'test'
